ssh_zone_handler/__init__.py
ssh_zone_handler/base.py
ssh_zone_handler/bind.py
ssh_zone_handler/cli.py
ssh_zone_handler/knot.py
ssh_zone_handler/static.py
ssh_zone_handler/types.py
ssh_zone_handler-0.4.0.dist-info/METADATA
ssh_zone_handler-0.4.0.dist-info/WHEEL
ssh_zone_handler-0.4.0.dist-info/entry_points.txt
ssh_zone_handler-0.4.0.dist-info/licenses/LICENSE
ssh_zone_handler-0.4.0.dist-info/RECORD
