Metadata-Version: 2.4
Name: ssh-zone-handler
Version: 0.4.0
Summary: SSH commands to provide Secondary DNS self-service.
License-Expression: MIT
License-File: LICENSE
Author: Andreas Olsson
Author-email: andreas@arrakis.se
Requires-Python: >=3.10, <3.15
Classifier: Programming Language :: Python :: 3
Classifier: Programming Language :: Python :: 3.10
Classifier: Programming Language :: Python :: 3.11
Classifier: Programming Language :: Python :: 3.12
Classifier: Programming Language :: Python :: 3.13
Classifier: Programming Language :: Python :: 3.14
Requires-Dist: pydantic (>=2.12.3,<3)
Requires-Dist: pyyaml (>=6.0.3,<7)
Project-URL: Repository, https://github.com/andreaso/ssh-zone-handler
